CHANGELOG.txt
LICENSE.txt
MANIFEST.in
README.txt
setup.py
Findline.egg-info/PKG-INFO
Findline.egg-info/SOURCES.txt
Findline.egg-info/dependency_links.txt
Findline.egg-info/top_level.txt
Fullline/__init__.py